{
    "data": {
        "text": "Lea atentamente el siguiente intercambio de tweets:\n\nDado el siguiente discurso de odio:\n\nalgo se pudre en el perú es el caos organizado surrealista subsahariano nuestra realidad https://t co/3hms5jyx7v\n\nSe responde lo siguiente:\n\nEste tweet es subjetivo y no proporciona suficientes datos o evidencia para llegar a una conclusiónde que \\\\\"algo se ha put",
        "number": "129",
        "hs": "algo se pudre en el perú es el caos organizado surrealista subsahariano nuestra realidad https://t co/3hms5jyx7v",
        "cn": "Este tweet es subjetivo y no proporciona suficientes datos o evidencia para llegar a una conclusiónde que \\\"algo se ha put",
        "model": "Mistral-7B-Instruct-v0.2_justification",
        "comparison_text": "No es cierto que algo se pudre en el país es realidad. ",
        "comparison_model": "flan-t5-base_finetuned_premises_allcn"
    }
}