{
    "data": {
        "number": "104",
        "hs": "la inmigraciòn de africa y países árebes es una estrategia para entrar a europa y atacarla desde dentro como hace mil años hicieron los barbaros para destruir el imperio romano el islan ataca una europa lacsa en leyes y desunida marina lepen tiene razón nada d inmigrantes https://t co/nzduyei7x5",
        "cn": "No es cierto que la inmigración de los países árebes es una estrategia para entrar a Europa y atacarla, y eso no tiene razón a los inmigrantes. ",
        "model": "flan-t5-base_finetuned_premises_allcn",
        "comparison_text": "Es injusto generalizar que todos quienes emigran de África o de Países Árabe tengan intenciones malas hacia Europa.",
        "comparison_model": "Mistral-7B-Instruct-v0.2_collective"
    }
}